[
    {
        "id": 0,
        "name": "Beg",
        "icon": "🙏",
        "output_item": "coins",
        "output_amount": 0.1,
        "energy_type": "energy",
        "energy_drain_rate": 0.1,
        "skill": "",
        "skill_exp_rate": 0,
        "unlock_conditions": [],
        "description": "Beg for coins on the streets.",
        "status_description": "You are begging for coins."
    },
    {
        "id": 1,
        "name": "Rob Beggars",
        "icon": "🦹",
        "output_item": "coins",
        "output_amount": 0.2,
        "energy_type": "energy",
        "energy_drain_rate": 0.1,
        "skill": "thieving",
        "skill_exp_rate": 0.25,
        "unlock_conditions": ["thieving"],
        "description": "Rob beggars on the streets.",
        "status_description": "You are robbing beggars for coins."
    },
    {
        "id": 2,
        "name": "Clean Stables",
        "icon": "",
        "output_item": "coins",
        "output_amount": 0.2,
        "energy_type": "energy",
        "energy_drain_rate": 0.5,
        "skill": "",
        "skill_exp_rate": 0,
        "unlock_conditions": ["manual labour"],
        "description": "Clean up after animals. Great for stamina training!",
        "status_description": "Scrubbing nasty things."
    },
    {
        "id": 3,
        "name": "Fishing",
        "icon": "🎣",
        "output_item": "fish",
        "output_amount": 0.3,
        "energy_type": "energy",
        "energy_drain_rate": 0.05,
        "skill": "fishing",
        "skill_exp_rate": 0.25,
        "unlock_conditions": ["fishing"],
        "description": "Now just to find some fish. Sell fish for gold.",
        "status_description": "Fishing at local ponds."
    },
    {
        "id": 4,
        "name": "Plant Caring",
        "icon": "🌼",
        "output_item": "plants",
        "output_amount": 0.1,
        "energy_type": "energy",
        "energy_drain_rate": 0.1,
        "skill": "farming",
        "skill_exp_rate": 0.25,
        "unlock_conditions": ["farming"],
        "description": "What do I do with this pot? I think someone wants to buy plants.",
        "status_description": "Taking care of some plant, not sure what."
    },
    {
        "id": 5,
        "name": "Cheat for testing",
        "icon": "",
        "output_item": "coins",
        "output_amount": 1,
        "energy_type": "energy",
        "energy_drain_rate": 0.1,
        "skill": "",
        "skill_exp_rate": 0,
        "unlock_conditions": [],
        "description": "Cheat for testing",
        "status_description": "CHEATING OMG!!!!."
    }
]
